mod17/__init__.py
mod17/calibration.py
mod17/science.py
mod17/sensitivity.py
mod17/srs.py
mod17/utils.py
mod17/viirs.py
mod17/data/MOD17_BPLUT_C5.1_MERRA_NASA.csv
mod17/data/MOD17_BPLUT_CX.X_MERRA_NASA.csv
mod17-1.0.0.dist-info/LICENSE
mod17-1.0.0.dist-info/METADATA
mod17-1.0.0.dist-info/WHEEL
mod17-1.0.0.dist-info/top_level.txt
mod17-1.0.0.dist-info/RECORD
