Metadata-Version: 2.1
Name: mod17
Version: 1.0.0
Summary: Python tools for MOD17 algorithm
Author: K. Arthur Endsley
Author-email: "K. Arthur Endsley" <arthur.endsley@ntsg.umt.edu>
License: MIT License
Classifier: Programming Language :: Python :: 3
Classifier: Development Status :: 3 - Alpha
Classifier: Intended Audience :: Science/Research
Classifier: Topic :: Scientific/Engineering
Requires-Python: >=3.8
License-File: LICENSE
Requires-Dist: h5py >=3.7.0
Requires-Dist: netCDF4 >=1.5.7
Requires-Dist: numpy >=1.21.0
Requires-Dist: scipy >=1.7.0
Requires-Dist: xarray >=0.19.0
Requires-Dist: suntransit >=0.1.0
Requires-Dist: tqdm >=4.60.0
Requires-Dist: fire >=0.4.0
Provides-Extra: calibration
Requires-Dist: pymc >=5.0.0 ; extra == 'calibration'
Requires-Dist: pytensor >=2.18.0 ; extra == 'calibration'
Requires-Dist: arviz >=0.13.0 ; extra == 'calibration'
Provides-Extra: docs
Requires-Dist: pdoc3 >=0.9.2 ; extra == 'docs'
Provides-Extra: sensitivity
Requires-Dist: SALib >=1.4.5 ; extra == 'sensitivity'
